farm/__init__.py
farm/api/__init__.py
farm/api/app.py
farm/api/routes/__init__.py
farm/api/routes/files.py
farm/api/routes/memory.py
farm/cli/__init__.py
farm/cli/main.py
farm/core/__init__.py
farm/core/indexer.py
farm/core/memory.py
farm/core/storage.py
farm/mcp/__init__.py
farm/mcp/server.py
farm/models/__init__.py
farm/models/schemas.py
farm/utils/__init__.py
farm/utils/helpers.py
farm_memory-0.1.2.dist-info/METADATA
farm_memory-0.1.2.dist-info/WHEEL
farm_memory-0.1.2.dist-info/entry_points.txt
farm_memory-0.1.2.dist-info/RECORD
