Metadata-Version: 2.4
Name: farm-memory
Version: 0.1.2
Summary: Filesystem As Remote Memory - Agent memory storage system
Requires-Python: >=3.10
Requires-Dist: aiofiles>=24.0.0
Requires-Dist: duckdb>=1.0.0
Requires-Dist: fastapi>=0.115.0
Requires-Dist: mcp>=1.0.0
Requires-Dist: pydantic>=2.0.0
Requires-Dist: sentence-transformers>=3.0.0
Requires-Dist: typer>=0.15.0
Requires-Dist: uvicorn[standard]>=0.32.0
Provides-Extra: dev
Requires-Dist: httpx>=0.28.0; extra == 'dev'
Requires-Dist: pytest-asyncio>=0.24.0; extra == 'dev'
Requires-Dist: pytest>=8.0.0; extra == 'dev'
Requires-Dist: ruff>=0.8.0; extra == 'dev'
